{
    "EDFH": {
        "elevation": 1649,
        "runways": "03,21",
        "transAlt": 5000,
        "maxInitialClimb": 7000,
        "intersections": {"03": "B1,B2,C,D", "21": "F,G,E"},
        "appSI": "EIF,PFA,RUD,GIN,KTG",
        "sids": {
            "initial": 5000,
            "climbvia": true,
            "ULKIG": {
                "E": {
                    "1":{
                        "rwy": "03",
                        "prio": 2
                    }
                },
                "T": {
                    "2":{
                        "rwy": "03",
                        "prio": 1,
                        "wtc": "HJ"
                    }
                },
                "S": {
                    "3":{
                        "rwy": "21",
                        "prio": 1
                    }
                },
                "L": {
                    "4":{
                        "rwy": "21",
                        "prio": 2
                    }
                }
			},
			"OLIVI": {
                "S": {
                    "1":{
                        "rwy": "21",
                        "prio": 1
                    }
                }
			},
			"GEBDA": {
                "E": {
                    "1":{
                        "rwy": "03",
                        "prio": 1
                    }
                },
                "L": {
                    "2":{
                        "rwy": "21",
                        "prio": 1
                    }
                }
			},
			"IDARO": {
                "E": {
                    "1":{
                        "rwy": "03",
                        "prio": 1
                    }
                },
                "T": {
                    "1":{
                        "rwy": "03",
                        "prio": 2
                    }
                },
                "Y": {
                    "1":{
                        "rwy": "21",
                        "prio": 1
                    }
                }
			},
			"RUDOT": {
                "E": {
                    "1":{
                        "rwy": "03",
                        "prio": 1
                    }
                },
                "T": {
                    "1":{
                        "rwy": "03",
                        "prio": 2
                    }
                },
                "S": {
                    "1":{
                        "rwy": "21",
                        "prio": 1
                    }
                },
                "L": {
                    "1":{
                        "rwy": "21",
                        "prio": 2
                    }
                }
			}
        }
    }
}
